AUTHORS
LICENSE
MANIFEST.in
README.rst
setup.cfg
setup.py
django_selectable_select2.egg-info/PKG-INFO
django_selectable_select2.egg-info/SOURCES.txt
django_selectable_select2.egg-info/dependency_links.txt
django_selectable_select2.egg-info/not-zip-safe
django_selectable_select2.egg-info/top_level.txt
selectable_select2/__init__.py
selectable_select2/base.py
selectable_select2/forms.py
selectable_select2/widgets.py
selectable_select2/static/selectable_select2/js/jquery.dj.selectable.select2.js
selectable_select2/static/selectable_select2/js/jquery.django.admin.fix.js