Metadata-Version: 1.1
Name: django-selectable-select2
Version: 0.4.0
Summary: plugin for django-selectable (to use with select2 UI)
Home-page: https://bitbucket.org/slafs/django-selectable-select2/
Author: Slawek Ehlert
Author-email: slafs@op.pl
License: BSD
Platform: UNKNOWN
Classifier: Development Status :: 4 - Beta
Classifier: Environment :: Web Environment
Classifier: Framework :: Django
Classifier: Intended Audience :: Developers
Classifier: License :: OSI Approved :: BSD License
Classifier: Operating System :: OS Independent
Classifier: Programming Language :: Python
Classifier: Programming Language :: Python :: 2.6
Classifier: Programming Language :: Python :: 2.7
Classifier: Topic :: Utilities
